content_tracker/__init__.py
content_tracker/_version.py
content_tracker/cli.py
content_tracker/main.py
content_tracker/models.py
content_tracker/databases/__init__.py
content_tracker/databases/base.py
content_tracker/databases/bigquery.py
content_tracker/databases/instance_store.py
content_tracker/notifiers/__init__.py
content_tracker/notifiers/base.py
content_tracker/notifiers/webhook.py
content_tracker/providers/__init__.py
content_tracker/providers/base.py
content_tracker-0.1.0.dist-info/METADATA
content_tracker-0.1.0.dist-info/WHEEL
content_tracker-0.1.0.dist-info/licenses/LICENSE
content_tracker-0.1.0.dist-info/RECORD
