Metadata-Version: 2.1
Name: content-tracker
Version: 0.1.0
Summary: Tracking changes in arbitrary content.
Project-URL: Homepage, https://github.com/speg03/content-tracker
Project-URL: Repository, https://github.com/speg03/content-tracker
Author-email: Takahiro Yano <speg03@gmail.com>
License-Expression: MIT
License-File: LICENSE
Keywords: changes,content,diff,tracking
Classifier: Development Status :: 3 - Alpha
Classifier: Environment :: Console
Classifier: Intended Audience :: Developers
Classifier: License :: OSI Approved :: MIT License
Classifier: Operating System :: OS Independent
Classifier: Programming Language :: Python :: 3.7
Classifier: Programming Language :: Python :: 3.8
Classifier: Programming Language :: Python :: 3.9
Classifier: Programming Language :: Python :: 3.10
Classifier: Programming Language :: Python :: 3.11
Classifier: Topic :: Software Development :: Libraries :: Python Modules
Classifier: Topic :: Text Processing
Requires-Python: >=3.7
Requires-Dist: typer<1.0,>=0.9
Provides-Extra: bigquery
Requires-Dist: google-cloud-bigquery~=3.10; extra == 'bigquery'
Provides-Extra: test
Requires-Dist: pytest; extra == 'test'
Requires-Dist: pytest-cov; extra == 'test'
